metamart_source_snowflake/__init__.py
metamart_source_snowflake/adapters.py
metamart_source_snowflake/base.py
metamart_source_snowflake/loader.py
metamart_source_snowflake/models.py
metamart_source_snowflake/package_definitions.py
metamart_source_snowflake-0.1.2.dist-info/METADATA
metamart_source_snowflake-0.1.2.dist-info/WHEEL
metamart_source_snowflake-0.1.2.dist-info/RECORD
