Metadata-Version: 2.1
Name: metamart_source_snowflake
Version: 0.1.2
Summary: 
Home-page: https://www.metamart.io/
License: ELv2
Author: Ian Eaves
Author-email: ian@metamart.io
Requires-Python: >=3.8,<4.0
Classifier: License :: Other/Proprietary License
Classifier: Programming Language :: Python :: 3
Classifier: Programming Language :: Python :: 3.8
Classifier: Programming Language :: Python :: 3.9
Classifier: Programming Language :: Python :: 3.10
Classifier: Programming Language :: Python :: 3.11
Classifier: Programming Language :: Python :: 3.12
Requires-Dist: PyYAML (>=6.0,<7.0)
Requires-Dist: metamart-schemas (>=0.2.6,<0.3.0)
Requires-Dist: multimethod (>=1.8,<2.0,!=1.11)
Requires-Dist: pydantic (>=1.9.1,<2.0.0)
Requires-Dist: snowflake-connector-python (>=3.0.0,<4.0.0)
Project-URL: Documentation, https://docs.metamart.io/
Project-URL: Repository, https://github.com/meta-mart/metamart-core/tree/master/metamart-integrations/source-snowflake
